Workbook

Sheet P&L Statement 
A1: P & L Statement (Given)
A2: (in thousand)
B3: 2023 | C3: 2024 | D3: 2025
A4: Revenues | B4: 33723297 | C4: 39000966 | D4: 45183036
A5: Cost of revenue | B5: 19715368 | C5: 21038464 | D5: 23275329
A6: Sales and Marketing | B6: 2657883 | C6: 2917554 | D6: 3301306
A7: Technology and development | B7: 2675758 | C7: 2925295 | D7: 3391390
A8: General and administrative | B8: 1720285 | C8: 1702039 | D8: 1888408
A9: Operating income | B9: =SUM(B4-(B5+B6+B7+B8)) -> 6954003 | C9: =SUM(C4-(C5+C6+C7+C8)) -> 10417614 | D9: =SUM(D4-(D5+D6+D7+D8)) -> 13326603
A10: Other income (expense):
A11: Interest Expense | B11: -699826 | C11: -718733 | D11: -776510
A12: Interest and Other Income ( Expense) | B12: -48772 | C12: 266776 | D12: 172459
A13: Income before income taxes | B13: =SUM(B9:B12) -> 6205405 | C13: =SUM(C9:C12) -> 9965657 | D13: =SUM(D9:D12) -> 12722552
A14: Provison for income taxes | B14: -797415 | C14: -1254026 | D14: -1741351
A15: Net Income | B15: =SUM(B13:B14) -> 5407990 | C15: =SUM(C13:C14) -> 8711631 | D15: =SUM(D13:D14) -> 10981201
A17: Earnig per share
A18: Basic | B18: 1.22 | C18: 2.03 | D18: 2.58
A19: Diluted | B19: 1.2 | C19: 1.98 | D19: 2.53
A21: Weighted Average shares of common stock outstanding
A22: Basic | B22: 4415712 | C22: 4295191 | D22: 4249512
A23: Diluted | B23: 4494966 | C23: 4392608 | D23: 4343863

Sheet Balance Sheet Input 
A1: Balance Sheet | B1: 2023 | C1: 2024 | D1: 2025
A2: Asset
A3: Current asset
A4: Cash and cash equivalents | B4: 7116913 | C4: 7804733 | D4: 9033681 | F4: Cashflow
A5: Short-term investments | B5: 20973 | C5: 1779006 | D5: 28678
A6: Other current assets | B6: 2780247 | C6: 3516640 | D6: 3957832 | F6: Other items
A7: Total current assets | B7: =SUM(B4:B6) -> 9918133 | C7: =SUM(C4:C6) -> 13100379 | D7: =SUM(D4:D6) -> 13020191
A8: Content assets, net | B8: 31658056 | C8: 32452462 | D8: 32778392 | F8: Schedules
A9: Property and equipment, net | B9: 1491444 | C9: 1593756 | D9: 2004350 | F9: Schedules
A10: Other non-current assets | B10: 5664359 | C10: 6483777 | D10: 7794060
A11: Total assets | B11: =SUM(B7:B10) -> 48731992 | C11: =SUM(C7:C10) -> 53630374 | D11: =SUM(D7:D10) -> 55596993
A12: Liabilities and Stockholders’ Equity
A13: Current liabilities:
A14: Current content liabilities | B14: 4466470 | C14: 4393681 | D14: 4084854
A15: Accounts payable | B15: 747412 | C15: 899909 | D15: 900612 | F15: Other items
A16: Accrued expenses and other liabilities | B16: 1803960 | C16: 2156544 | D16: 3220869 | F16: Other items
A17: Deferred revenue | B17: 1442969 | C17: 1520813 | D17: 1775730 | F17: Other items
A18: Short-term debt | B18: 399844 | C18: 1784453 | D18: 998865
A19: Total current liabilities | B19: =SUM(B14:B18) -> 8860655 | C19: =SUM(C14:C18) -> 10755400 | D19: =SUM(D14:D18) -> 10980930
A20: Non-current content liabilities | B20: 2578173 | C20: 1780806 | D20: 1579476
A21: Long-term debt | B21: 14143417 | C21: 13798351 | D21: 13463971
A22: Other non-current liabilities | B22: 2561434 | C22: 2552250 | D22: 2957128
A23: Total liabilities | B23: =SUM(B19:B22) -> 28143679 | C23: =SUM(C19:C22) -> 28886807 | D23: =SUM(D19:D22) -> 28981505
A24: Commitments and contingencies (Note 9)
A25: Stockholders’ equity:
A26: preferred stock
A27: Common Stock | B27: 5145172 | C27: 6252126 | D27: 7286410
A28: Treasury Stock | B28: -6922200 | C28: -13171638 | D28: -22372658
A29: Accumulated other comprehensive income(bs) | B29: -223945 | C29: 362162 | D29: -580382
A30: Retained earnings | B30: 22589286 | C30: 31300917 | D30: 42282118
A31: Total Stockholder Equity | B31: =SUM(B27:B30) -> 20588313 | C31: =SUM(C27:C30) -> 24743567 | D31: =SUM(D27:D30) -> 26615488
A32: Total liabilities and stockholding equity | B32: =SUM(B23+B31) -> 48731992 | C32: =SUM(C23,C31) -> 53630374 | D32: =SUM(D23,D31) -> 55596993
A34: Check | B34: =B11=B32 -> TRUE | C34: =C32=C11 -> TRUE | D34: =D32=D11 -> TRUE

Sheet Revenue Modeling  
A1: Revenue Source (In Thousand ) | M1: Assumption
M2: Revenue Growth with avg rate
A3: Financial Results | B3: 2023(Given) | C3: 2024(Given) | D3: 2025(Given) | E3: 2026(Forcast) | F3: 2027(Forcast) | G3: 2028(Forcast)
A4: Streaming revenues | B4: 33640458 | C4: 39000966 | D4: 45183036 | E4: =D4*E6+D4 -> 52363925 | F4: =E4*F6+E4 -> 60675116 | G4: =F4*G6+F4 -> 70311800
A5: DVD revenues | B5: 82839 | C5: 0 | D5: 0 | E5: =D5*E6+D5 -> 0 | F5: =E5*F6+E5 -> 0 | G5: =F5*G6+F5 -> 0
A6: Growth% | C6: =C4/B4-1 -> 0.15934706 | D6: =D4/C4-1 -> 0.15851069 | E6: =AVERAGE(C6:D6) -> 0.15892887 | F6: =AVERAGE(D6:E6) -> 0.15871978 | G6: =AVERAGE(E6:F6) -> 0.15882433
A7: Total Revenue | B7: =SUM(B4:B5) -> 33723297 | C7: =SUM(C4:C5) -> 39000966 | D7: =SUM(D4:D5) -> 45183036 | E7: =SUM(E4:E5) -> 52363925 | F7: =SUM(F4:F5) -> 60675116 | G7: =SUM(G4:G5) -> 70311800
A9: UCAN(United States and Canada)
A10: Revenue | B10: 14873783 | C10: 17359369 | D10: 19957152 | E10: =D10*E12+D10 -> 22718815 | F10: =E10*F12+E10 -> 25536254 | G10: =F10*G12+F10 -> 28375796
A11: Average paid Membership | B11: 37 | C11: 37 | D11: 37 | E11: =AVERAGE(B11:D11) -> 37 | F11: =AVERAGE(C11:E11) -> 37 | G11: =AVERAGE(D11:F11) -> 37
A12: Growth% | C12: =C10/B10-1 -> 0.16711189 | D12: =D10/C10-1 -> 0.14964732 | E12: =AVERAGE(C12:D12)-2% -> 0.1383796 | F12: =AVERAGE(D12:E12)-2% -> 0.12401346 | G12: =AVERAGE(E12:F12)-2% -> 0.11119653
A14: EMEA(Europe, Middle East, and Africa)
A15: Revenue | B15: 10556487 | C15: 12387035 | D15: 14514646 | E15: =D15*E17+D15 -> 17019628 | F15: =E15*F17+E15 -> 19949933 | G15: =F15*G17+F15 -> 23388855
A16: Average paid Membership | B16: 37 | C16: 37 | D16: 37 | E16: =AVERAGE(B16:D16) -> 37 | F16: =AVERAGE(C16:E16) -> 37 | G16: =AVERAGE(D16:F16) -> 37
A17: Growth% | C17: =C15/B15-1 -> 0.17340504 | D17: =D15/C15-1 -> 0.17176112 | E17: =AVERAGE(C17:D17) -> 0.17258308 | F17: =AVERAGE(D17:E17) -> 0.1721721 | G17: =AVERAGE(E17:F17) -> 0.17237759
A19: LATAM (Latin America)
A20: Revenue | B20: 4446461 | C20: 4839816 | D20: 5357521 | E20: =D20*E22+D20 -> 5881038.3 | F20: =E20*F22+E20 -> 6482916.2 | G20: =F20*G22+F20 -> 7131397.2
A21: Average paid Membership | B21: 37 | C21: 37 | D21: 37 | E21: =AVERAGE(B21:D21) -> 37 | F21: =AVERAGE(C21:E21) -> 37 | G21: =AVERAGE(D21:F21) -> 37
A22: Growth% | C22: =C20/B20-1 -> 0.088464736 | D22: =D20/C20-1 -> 0.10696791 | E22: =AVERAGE(C22:D22) -> 0.097716323 | F22: =AVERAGE(D22:E22) -> 0.10234212 | G22: =AVERAGE(E22:F22) -> 0.10002922
A24: APAC (Asia-Pacific)
A25: Revenue | B25: 3763727 | C25: 4414746 | D25: 5353717 | E25: =D25*E27+D25 -> 6386078.5 | F25: =E25*F27+E25 -> 7680921.4 | G25: =F25*G27+F25 -> 9200173.3
A26: Average paid Membership | B26: 37 | C26: 37 | D26: 37 | E26: =AVERAGE(B26:D26) -> 37 | F26: =AVERAGE(C26:E26) -> 37 | G26: =AVERAGE(D26:F26) -> 37
A27: Growth% | C27: =C25/B25-1 -> 0.1729719 | D27: =D25/C25-1 -> 0.2126897 | E27: =AVERAGE(C27:D27) -> 0.1928308 | F27: =AVERAGE(D27:E27) -> 0.20276025 | G27: =AVERAGE(E27:F27) -> 0.19779552

Sheet Other Modeling 
A1: Other Items
A3: (In thousands) | B3: 2023(Given) | C3: 2024(Given) | D3: 2025(Given) | E3: 2026(Forcast) | F3: 2027(Forcast) | G3: 2028(Forcast)
A4: Cost of Good Sold | B4: ='P&L Statement '!$B$5 -> 19715368 | C4: ='P&L Statement '!$C$5 -> 21038464 | D4: ='P&L Statement '!$D$5 -> 23275329 | E4: ='Revenue Modeling '!$E$7*'Other Modeling '!$E$5 -> 28611479 | F4: ='Revenue Modeling '!F7*'Other Modeling '!F5 -> 33152687 | G4: ='Revenue Modeling '!G7*'Other Modeling '!G5 -> 38418140
A5: as a % revenue | B5: =B4/'Revenue Modeling '!B7 -> 0.5846216 | C5: =C4/'Revenue Modeling '!C7 -> 0.53943443 | D5: =D4/'Revenue Modeling '!D7 -> 0.51513424 | E5: =AVERAGE($B$5:$D$5) -> 0.54639676 | F5: =AVERAGE($B$5:$D$5) -> 0.54639676 | G5: =AVERAGE($B$5:$D$5) -> 0.54639676
A7: Sales and Marketing | B7: ='P&L Statement '!$B$6 -> 2657883 | C7: ='P&L Statement '!$C$6 -> 2917554 | D7: ='P&L Statement '!$D$6 -> 3301306 | E7: =E8*'Revenue Modeling '!E7 -> 3956737.5 | F7: =F8*'Revenue Modeling '!F7 -> 4584750 | G7: =G8*'Revenue Modeling '!G7 -> 5312919.8
A8: as a % revenue | B8: =B7/'Revenue Modeling '!B7 -> 0.078814447 | C8: =C7/'Revenue Modeling '!C7 -> 0.074807224 | D8: =D7/'Revenue Modeling '!D7 -> 0.073065165 | E8: =AVERAGE($B$8:$D$8) -> 0.075562279 | F8: =AVERAGE($B$8:$D$8) -> 0.075562279 | G8: =AVERAGE($B$8:$D$8) -> 0.075562279
A10: Technology and development | B10: ='P&L Statement '!B7 -> 2675758 | C10: ='P&L Statement '!C7 -> 2925295 | D10: ='P&L Statement '!D7 -> 3391390 | E10: =E11*'Revenue Modeling '!E7 -> 4004254.1 | F10: =F11*'Revenue Modeling '!F7 -> 4639808.4 | G10: =G11*'Revenue Modeling '!G7 -> 5376722.8
A11: as a % revenue | B11: =B10/'Revenue Modeling '!B7 -> 0.079344496 | C11: =C10/'Revenue Modeling '!C7 -> 0.075005706 | D11: =D10/'Revenue Modeling '!D7 -> 0.075058923 | E11: =AVERAGE($B$11:$D$11) -> 0.076469708 | F11: =AVERAGE($B$11:$D$11) -> 0.076469708 | G11: =AVERAGE($B$11:$D$11) -> 0.076469708
A13: General and administrative | B13: ='P&L Statement '!B8 -> 1720285 | C13: ='P&L Statement '!C8 -> 1702039 | D13: ='P&L Statement '!D8 -> 1888408 | E13: =E14*'Revenue Modeling '!E7 -> 2381639.4 | F13: =F14*'Revenue Modeling '!F7 -> 2759652.6 | G13: =G14*'Revenue Modeling '!G7 -> 3197952.6
A14: as a % revenue | B14: =B13/'Revenue Modeling '!B7 -> 0.051011768 | C14: =C13/'Revenue Modeling '!C7 -> 0.043640945 | D14: =D13/'Revenue Modeling '!D7 -> 0.041794624 | E14: =AVERAGE($B$14:$D$14) -> 0.045482446 | F14: =AVERAGE($B$14:$D$14) -> 0.045482446 | G14: =AVERAGE($B$14:$D$14) -> 0.045482446
A17: Other Current assets | B17: ='Balance Sheet Input '!B6 -> 2780247 | C17: ='Balance Sheet Input '!C6 -> 3516640 | D17: ='Balance Sheet Input '!D6 -> 3957832 | E17: =E18*'Revenue Modeling '!E7 -> 4586845.8 | F17: =F18*'Revenue Modeling '!F7 -> 5314868.9 | G17: =G18*'Revenue Modeling '!G7 -> 6158999.4
A18: as a % revenue | B18: =B17/'Revenue Modeling '!B7 -> 0.082442918 | C18: =C17/'Revenue Modeling '!C7 -> 0.090168023 | D18: =D17/'Revenue Modeling '!D7 -> 0.08759553 | E18: 0.08759553 | F18: 0.08759553 | G18: 0.08759553
A20: Accounts Payable | B20: ='Balance Sheet Input '!B15 -> 747412 | C20: ='Balance Sheet Input '!C15 -> 899909 | D20: ='Balance Sheet Input '!D15 -> 900612 | E20: =E21*E4/365 -> 1107088.2 | F20: =F21*F4/365 -> 1282805 | G20: =G21*G4/365 -> 1486545.6
A21: Days Payable | B21: =B20/B4*365 -> 13.837194 | C21: =C20/C4*365 -> 15.612679 | D21: =D20/D4*365 -> 14.123254 | E21: =D21 -> 14.123254 | F21: =E21 -> 14.123254 | G21: =F21 -> 14.123254
A23: ='Balance Sheet Input '!A16 -> Accrued expenses and other liabilities | B23: ='Balance Sheet Input '!B16 -> 1803960 | C23: ='Balance Sheet Input '!C16 -> 2156544 | D23: ='Balance Sheet Input '!D16 -> 3220869 | E23: =E24*'Revenue Modeling '!E7 -> 3143101.6 | F23: =F24*'Revenue Modeling '!F7 -> 3774067.6 | G23: =G24*'Revenue Modeling '!G7 -> 4535353.4
A24: as a % revenue | B24: ='Other Modeling '!B23/'Revenue Modeling '!B7 -> 0.05349299 | C24: ='Other Modeling '!C23/'Revenue Modeling '!C7 -> 0.05529463 | D24: ='Other Modeling '!D23/'Revenue Modeling '!D7 -> 0.071284918 | E24: =AVERAGE(B24:D24) -> 0.060024179 | F24: =AVERAGE(C24:E24) -> 0.062201242 | G24: =AVERAGE(D24:F24) -> 0.064503447
A26: ='Balance Sheet Input '!A17 -> Deferred revenue | B26: ='Balance Sheet Input '!B17 -> 1442969 | C26: ='Balance Sheet Input '!C17 -> 1520813 | D26: ='Balance Sheet Input '!D17 -> 1775730 | E26: =E27*'Revenue Modeling '!E7 -> 2113469.8 | F26: =F27*'Revenue Modeling '!F7 -> 2399826.9 | G26: =G27*'Revenue Modeling '!G7 -> 2794052
A27: as a % revenue | B27: =B26/'Revenue Modeling '!B7 -> 0.042788491 | C27: =C26/'Revenue Modeling '!C7 -> 0.038994239 | D27: =D26/'Revenue Modeling '!D7 -> 0.039300812 | E27: =AVERAGE(B27:D27) -> 0.040361181 | F27: =AVERAGE(C27:E27) -> 0.039552077 | G27: =AVERAGE(D27:F27) -> 0.039738023

Sheet Schedules
A1: Property, Plant and Equipment
A2: (IN thousand) | B2: 2023(Given) | C2: 2024(Given) | D2: 2025(Given) | E2: 2026(Forcast) | F2: 2027(Forcast) | G2: 2028(Forcast)
A3: Beginning Balance | C3: =B6 -> 1491444 | D3: =C6 -> 1593756 | E3: =D6 -> 2004350 | F3: =E6 -> 2320828.3 | G3: =F6 -> 2622480.5
A4: add: Capex | C4: =SUM(C5:C6)-C3 -> 431226 | D4: =SUM(D5:D6)-D3 -> 743983 | E4: =$D$4 -> 743983 | F4: =$D$4 -> 743983 | G4: =$D$4 -> 743983 | I4: Assumption : | J4: Capex Constant
A5: less: Depreciation | B5: 356947 | C5: 328914 | D5: 333389 | E5: =(E3+E4)/E8 -> 427504.74 | F5: =(F3+F4)/F8 -> 442330.71 | G5: =(G3+G4)/G8 -> 453165.19
A6: Closing Balance | B6: ='Balance Sheet Input '!B9 -> 1491444 | C6: ='Balance Sheet Input '!C9 -> 1593756 | D6: ='Balance Sheet Input '!D9 -> 2004350 | E6: =(E3+E4)-E5 -> 2320828.3 | F6: =(F3+F4)-F5 -> 2622480.5 | G6: =(G3+G4)-G5 -> 2913298.4
A8: Useful Life | C8: =(C3+C4)/C5 -> 5.8455098 | D8: =(D3+D4)/D5 -> 7.012046 | E8: =AVERAGE(C8:D8) -> 6.4287779 | F8: =E8+0.5 -> 6.9287779 | G8: =F8+0.5 -> 7.4287779 | K8: Notes
L9: usefullife/Depriciatiomn
A10: Content Assets
A11: Beginning Balance | C11: =B14 -> 31658056 | D11: =C14 -> 32452462 | E11: =D14 -> 32778392 | F11: =E14 -> 33333027 | G11: =F14 -> 33706316
A12: add: Addition | C12: =SUM(C13:C14)-C11 -> 16095923 | D12: =SUM(D13:D14)-D11 -> 16748096 | E12: =$D$12 -> 16748096 | F12: =$D$12 -> 16748096 | G12: =$D$12 -> 16748096
A13: less: Amortisation | C13: 15301517 | D13: 16422166 | E13: =(E11+E12)/E16 -> 16193461 | F13: =(F11+F12)/F16 -> 16374807 | G13: =(G11+G12)/G16 -> 16496860
A14: Closing Balance | B14: ='Balance Sheet Input '!B8 -> 31658056 | C14: ='Balance Sheet Input '!C8 -> 32452462 | D14: ='Balance Sheet Input '!D8 -> 32778392 | E14: =(E11+E12)-E13 -> 33333027 | F14: =(F11+F12)-F13 -> 33706316 | G14: =(G11+G12)-G13 -> 33957552
A16: Useful life | C16: =(C11+C12)/C13 -> 3.1208657 | D16: =(D11+D12)/D13 -> 2.9959847 | E16: =AVERAGE(C16:D16) -> 3.0584252 | F16: =E16 -> 3.0584252 | G16: =F16 -> 3.0584252
A19: Debt Schedule
A20: Beginning Balance | C20: =B23 -> 14143417 | D20: =C23 -> 13798351 | E20: =D23 -> 13463971 | F20: =E23 -> 13462965 | G20: =F23 -> 13461415
A21: add: Dedt Took | C21: 0 | D21: 0
A22: less: Dedt paid | C22: =C23-C20 -> -345066 | D22: =D23-D20 -> -334380 | E22: -1006 | F22: -1550 | G22: =-SUM(1634 + 1998) -> -3632
A23: Closing Balance | B23: ='Balance Sheet Input '!B21 -> 14143417 | C23: ='Balance Sheet Input '!C21 -> 13798351 | D23: ='Balance Sheet Input '!D21 -> 13463971 | E23: =SUM(E20,E22) -> 13462965 | F23: =SUM(F20,F22) -> 13461415 | G23: =SUM(G20,G22) -> 13457783
A25: Interest Expense | B25: ='P&L Statement '!B11 -> -699826 | C25: ='P&L Statement '!C11 -> -718733 | D25: ='P&L Statement '!D11 -> -776510 | E25: =E23*E26 -> -714624.02 | F25: =F23*F26 -> -714541.74 | G25: =G23*G26 -> -714348.95
A26: Interest Rate | B26: =B25/B23 -> -0.049480688 | C26: =C25/C23 -> -0.052088326 | D26: =D25/D23 -> -0.057673178 | E26: =AVERAGE($B$26:$D$26) -> -0.053080731 | F26: =AVERAGE($B$26:$D$26) -> -0.053080731 | G26: =AVERAGE($B$26:$D$26) -> -0.053080731

Sheet P&l Statement Forcasted 
A1: P & L Statement
A2: (in thousand)
B3: 2023(Given) | C3: 2024(Given) | D3: 2025(Given) | E3: 2026(Forcast) | F3: 2027(Forcast) | G3: 2028(Forcast)
A5: Streaming Revenues | B5: ='Revenue Modeling '!B4 -> 33640458 | C5: ='Revenue Modeling '!C4 -> 39000966 | D5: ='Revenue Modeling '!D4 -> 45183036 | E5: ='Revenue Modeling '!E4 -> 52363925 | F5: ='Revenue Modeling '!F4 -> 60675116 | G5: ='Revenue Modeling '!G4 -> 70311800
A6: DVR | B6: ='Revenue Modeling '!B5 -> 82839 | C6: ='Revenue Modeling '!C5 -> 0 | D6: ='Revenue Modeling '!D5 -> 0 | E6: ='Revenue Modeling '!E5 -> 0 | F6: ='Revenue Modeling '!F5 -> 0 | G6: ='Revenue Modeling '!G5 -> 0
A7: Total Revenue | B7: =SUM(B5:B6) -> 33723297 | C7: =SUM(C5:C6) -> 39000966 | D7: =SUM(D5:D6) -> 45183036 | E7: =SUM(E5:E6) -> 52363925 | F7: =SUM(F5:F6) -> 60675116 | G7: =SUM(G5:G6) -> 70311800
A8: Revenues | B8: =B7 -> 33723297 | C8: =C7 -> 39000966 | D8: =D7 -> 45183036 | E8: =E7 -> 52363925 | F8: =F7 -> 60675116 | G8: =G7 -> 70311800
A9: Cost of good Sold | B9: ='Other Modeling '!B4-B16 -> 19358421 | C9: ='Other Modeling '!C4-C16 -> 20709550 | D9: ='Other Modeling '!D4-D16 -> 22941940 | E9: ='Other Modeling '!E4-E16 -> 28183974 | F9: ='Other Modeling '!F4-F16 -> 32710356 | G9: ='Other Modeling '!G4-G16 -> 37964975
A10: Gross Margin | B10: =B8-B9 -> 14364876 | C10: =C8-C9 -> 18291416 | D10: =D8-D9 -> 22241096 | E10: =E8-E9 -> 24179951 | F10: =F8-F9 -> 27964760 | G10: =G8-G9 -> 32346826
A11: Operating Expenses :
A12: Marketing | B12: ='Other Modeling '!B7 -> 2657883 | C12: ='Other Modeling '!C7 -> 2917554 | D12: ='Other Modeling '!D7 -> 3301306 | E12: ='Other Modeling '!E7 -> 3956737.5 | F12: ='Other Modeling '!F7 -> 4584750 | G12: ='Other Modeling '!G7 -> 5312919.8
A13: Technology and development | B13: ='Other Modeling '!B10 -> 2675758 | C13: ='Other Modeling '!C10 -> 2925295 | D13: ='Other Modeling '!D10 -> 3391390 | E13: ='Other Modeling '!E10 -> 4004254.1 | F13: ='Other Modeling '!F10 -> 4639808.4 | G13: ='Other Modeling '!G10 -> 5376722.8
A14: General and administrative | B14: ='Other Modeling '!B13 -> 1720285 | C14: ='Other Modeling '!C13 -> 1702039 | D14: ='Other Modeling '!D13 -> 1888408 | E14: ='Other Modeling '!E13 -> 2381639.4 | F14: ='Other Modeling '!F13 -> 2759652.6 | G14: ='Other Modeling '!G13 -> 3197952.6
A15: EBITDA | B15: =B10-(B12+B13+B14) -> 7310950 | C15: =C10-(C12+C13+C14) -> 10746528 | D15: =D10-(D12+D13+D14) -> 13659992 | E15: =E10-(E12+E13+E14) -> 13837320 | F15: =F10-(F12+F13+F14) -> 15980549 | G15: =G10-(G12+G13+G14) -> 18459230
A16: LESS: Deprication | B16: =Schedules!B5 -> 356947 | C16: =Schedules!C5 -> 328914 | D16: =Schedules!D5 -> 333389 | E16: =Schedules!E5 -> 427504.74 | F16: =Schedules!F5 -> 442330.71 | G16: =Schedules!G5 -> 453165.19
A17: EBIT | B17: =B15-B16 -> 6954003 | C17: =C15-C16 -> 10417614 | D17: =D15-D16 -> 13326603 | E17: =E15-E16 -> 13409815 | F17: =F15-F16 -> 15538218 | G17: =G15-G16 -> 18006065
A18: Interest Expense | B18: =Schedules!B25 -> -699826 | C18: =Schedules!C25 -> -718733 | D18: =Schedules!D25 -> -776510 | E18: =Schedules!E25 -> -714624.02 | F18: =Schedules!F25 -> -714541.74 | G18: =Schedules!G25 -> -714348.95
A19: Interest and Other Income ( Expense) | B19: ='P&L Statement '!B12 -> -48772 | C19: ='P&L Statement '!C12 -> 266776 | D19: ='P&L Statement '!D12 -> 172459 | E19: - | F19: - | G19: -
A20: EBT | B20: =SUM(B17:B19) -> 6205405 | C20: =SUM(C17:C19) -> 9965657 | D20: =SUM(D17:D19) -> 12722552 | E20: =SUM(E17:E19) -> 12695191 | F20: =SUM(F17:F19) -> 14823676 | G20: =SUM(G17:G19) -> 17291716
A21: Tax | B21: ='P&L Statement '!B14 -> -797415 | C21: ='P&L Statement '!C14 -> -1254026 | D21: ='P&L Statement '!D14 -> -1741351 | E21: =E20*E22 -> -1655492.1 | F21: =F20*F22 -> -1942440.4 | G21: =G20*G22 -> -2295824.8
A22: Tax rate @ | B22: =B21/B20 -> -0.1285033 | C22: =C21/C20 -> -0.12583475 | D22: =D21/D20 -> -0.1368712 | E22: =AVERAGE(B22:D22) -> -0.13040308 | F22: =AVERAGE(C22:E22) -> -0.13103635 | G22: =AVERAGE(D22:F22) -> -0.13277021
A23: PAT | B23: =SUM(B20+B21) -> 5407990 | C23: =SUM(C20+C21) -> 8711631 | D23: =SUM(D20+D21) -> 10981201 | E23: =SUM(E20+E21) -> 11039699 | F23: =SUM(F20+F21) -> 12881236 | G23: =SUM(G20+G21) -> 14995891

Sheet Balance Sheet Forcast 
A1: Balance Sheet | B1: 2023 | C1: 2024 | D1: 2025 | E1: 2026 | F1: 2027 | G1: 2028
A2: Asset
A3: Current asset
A4: Cash and cash equivalents | B4: 7116913 | C4: 7804733 | D4: 9033681 | E4: =D4+'Cash Flow Statement '!E25 -> 19038695 | F4: =E4+'Cash Flow Statement '!F25 -> 31608457 | G4: =F4+'Cash Flow Statement '!G25 -> 46573783
A5: Short-term investments | B5: 20973 | C5: 1779006 | D5: 28678 | E5: 28678 | F5: 28678 | G5: 28678
A6: Other current assets | B6: 2780247 | C6: 3516640 | D6: 3957832 | E6: ='Other Modeling '!E17 -> 4586845.8 | F6: ='Other Modeling '!F17 -> 5314868.9 | G6: ='Other Modeling '!G17 -> 6158999.4
A7: Total current assets | B7: =SUM(B4:B6) -> 9918133 | C7: =SUM(C4:C6) -> 13100379 | D7: =SUM(D4:D6) -> 13020191 | E7: =SUM(E4:E6) -> 23654219 | F7: =SUM(F4:F6) -> 36952004 | G7: =SUM(G4:G6) -> 52761461
A8: Content assets, net | B8: 31658056 | C8: 32452462 | D8: 32778392 | E8: =Schedules!E14 -> 33333027 | F8: =Schedules!F14 -> 33706316 | G8: =Schedules!G14 -> 33957552
A9: Property and equipment, net | B9: 1491444 | C9: 1593756 | D9: 2004350 | E9: =Schedules!E6 -> 2320828.3 | F9: =Schedules!F6 -> 2622480.5 | G9: =Schedules!G6 -> 2913298.4
A10: Other non-current assets | B10: 5664359 | C10: 6483777 | D10: 7794060 | E10: 7794060 | F10: 7794060 | G10: 7794060
A11: Total assets | B11: =SUM(B7:B10) -> 48731992 | C11: =SUM(C7:C10) -> 53630374 | D11: =SUM(D7:D10) -> 55596993 | E11: =SUM(E7:E10) -> 67102135 | F11: =SUM(F7:F10) -> 81074860 | G11: =SUM(G7:G10) -> 97426371
A12: Liabilities and Stockholders Equity
A13: Current liabilities:
A14: Current content liabilities | B14: 4466470 | C14: 4393681 | D14: 4084854 | E14: 4084854 | F14: 4084854 | G14: 4084854
A15: Accounts payable | B15: 747412 | C15: 899909 | D15: 900612 | E15: ='Other Modeling '!E20 -> 1107088.2 | F15: ='Other Modeling '!F20 -> 1282805 | G15: ='Other Modeling '!G20 -> 1486545.6
A16: Accrued expenses and other liabilities | B16: 1803960 | C16: 2156544 | D16: 3220869 | E16: ='Other Modeling '!E23 -> 3143101.6 | F16: ='Other Modeling '!F23 -> 3774067.6 | G16: ='Other Modeling '!G23 -> 4535353.4
A17: Deferred revenue | B17: 1442969 | C17: 1520813 | D17: 1775730 | E17: ='Other Modeling '!E26 -> 2113469.8 | F17: ='Other Modeling '!F26 -> 2399826.9 | G17: ='Other Modeling '!G26 -> 2794052
A18: Short-term debt | B18: 399844 | C18: 1784453 | D18: 998865 | E18: 998865 | F18: 998865 | G18: 998865
A19: Total current liabilities | B19: =SUM(B14:B18) -> 8860655 | C19: =SUM(C14:C18) -> 10755400 | D19: =SUM(D14:D18) -> 10980930 | E19: =SUM(E14:E18) -> 11447379 | F19: =SUM(F14:F18) -> 12540418 | G19: =SUM(G14:G18) -> 13899670
A20: Non-current content liabilities | B20: 2578173 | C20: 1780806 | D20: 1579476 | E20: 1579476 | F20: 1579476 | G20: 1579476
A21: Long-term debt | B21: 14143417 | C21: 13798351 | D21: 13463971 | E21: =Schedules!E23 -> 13462965 | F21: =Schedules!F23 -> 13461415 | G21: =Schedules!G23 -> 13457783
A22: Other non-current liabilities | B22: 2561434 | C22: 2552250 | D22: 2957128 | E22: 2957128 | F22: 2957128 | G22: 2957128
A23: Total liabilities | B23: =SUM(B19:B22) -> 28143679 | C23: =SUM(C19:C22) -> 28886807 | D23: =SUM(D19:D22) -> 28981505 | E23: =SUM(E19:E22) -> 29446948 | F23: =SUM(F19:F22) -> 30538437 | G23: =SUM(G19:G22) -> 31894057
A24: Commitments and contingencies (Note 9)
A25: Stockholders’ equity:
A26: preferred stock
A27: Common Stock | B27: 5145172 | C27: 6252126 | D27: 7286410 | E27: 7286410 | F27: 7286410 | G27: 7286410
A28: Treasury Stock | B28: -6922200 | C28: -13171638 | D28: -22372658 | E28: -22372658 | F28: -22372658 | G28: -22372658
A29: Accumulated other comprehensive income(bs) | B29: -223945 | C29: 362162 | D29: -580382 | E29: -580382 | F29: -580382 | G29: -580382
A30: Retained earnings | B30: 22589286 | C30: 31300917 | D30: 42282118 | E30: =D30 +'P&l Statement Forcasted '!E23 -> 53321817 | F30: =E30+'P&l Statement Forcasted '!F23 -> 66203053 | G30: =F30+'P&l Statement Forcasted '!G23 -> 81198944
A31: Total Stockholder Equity | B31: =SUM(B27:B30) -> 20588313 | C31: =SUM(C27:C30) -> 24743567 | D31: =SUM(D27:D30) -> 26615488 | E31: =SUM(E27:E30) -> 37655187 | F31: =SUM(F27:F30) -> 50536423 | G31: =SUM(G27:G30) -> 65532314
A32: Total liabilities and stockholding equity | B32: =SUM(B23+B31) -> 48731992 | C32: =SUM(C23,C31) -> 53630374 | D32: =SUM(D23,D31) -> 55596993 | E32: =SUM(E23,E31) -> 67102135 | F32: =SUM(F23,F31) -> 81074860 | G32: =SUM(G23,G31) -> 97426371
A34: Check | B34: =B11=B32 -> TRUE | C34: =C32=C11 -> TRUE | D34: =D32=D11 -> TRUE | E34: =E32=E11 -> TRUE | F34: =F32=F11 -> TRUE | G34: =G32=G11 -> TRUE
E37: =E11-E32 -> 0 | F37: =F11-F32 -> 0 | G37: =G11-G32 -> 0

Sheet Cash Flow Statement 
A1: Cash & Cash Equivalent
A3: (in thousand) | E3: 2026 | F3: 2027 | G3: 2028
A4: EBIT | E4: ='P&l Statement Forcasted '!E17 -> 13409815 | F4: ='P&l Statement Forcasted '!F17 -> 15538218 | G4: ='P&l Statement Forcasted '!G17 -> 18006065
A5: Operating Taxes | E5: =E4*E6 -> -1748681.3 | F5: =F4*F6 -> -2036071.3 | G5: =G4*G6 -> -2390669.1
A6: Operating Tax Rate | E6: ='P&l Statement Forcasted '!E22 -> -0.13040308 | F6: ='P&l Statement Forcasted '!F22 -> -0.13103635 | G6: ='P&l Statement Forcasted '!G22 -> -0.13277021
A7: NOPAT | E7: =SUM(E4:E5) -> 11661134 | F7: =SUM(F4:F5) -> 13502147 | G7: =SUM(G4:G5) -> 15615396
A8: Add: Deprication | E8: =Schedules!E5 -> 427504.74 | F8: =Schedules!F5 -> 442330.71 | G8: =Schedules!G5 -> 453165.19
A9: Add; Amortisation | E9: =Schedules!E13 -> 16193461 | F9: =Schedules!F13 -> 16374807 | G9: =Schedules!G13 -> 16496860
A10: Gross Cash Flow | E10: =SUM(E7:E9) -> 28282099 | F10: =SUM(F7:F9) -> 30319285 | G10: =SUM(G7:G9) -> 32565421
A11: Account Payable | E11: ='Other Modeling '!E20-'Other Modeling '!D20 -> 206476.17 | F11: ='Other Modeling '!F20-'Other Modeling '!E20 -> 175716.79 | G11: ='Other Modeling '!G20-'Other Modeling '!F20 -> 203740.63
A12: Deferred Revenue | E12: ='Other Modeling '!E26-'Other Modeling '!D26 -> 337739.85 | F12: ='Other Modeling '!F26-'Other Modeling '!E26 -> 286357.02 | G12: ='Other Modeling '!G26-'Other Modeling '!F26 -> 394225.09
A14: Accrued expenses and other Liablites | E14: ='Other Modeling '!E23-'Other Modeling '!D23 -> -77767.368 | F14: ='Other Modeling '!F23-'Other Modeling '!E23 -> 630965.96 | G14: ='Other Modeling '!G23-'Other Modeling '!F23 -> 761285.86
A15: Other Current Asstes | E15: =-SUM('Other Modeling '!E17-'Other Modeling '!D17) -> -629013.78 | F15: =-SUM('Other Modeling '!F17-'Other Modeling '!E17) -> -728023.16 | G15: =-SUM('Other Modeling '!G17-'Other Modeling '!F17) -> -844130.48
A16: Investments in Working Capital | E16: =SUM(E11:E15) -> -162565.14 | F16: =SUM(F11:F15) -> 365016.61 | G16: =SUM(G11:G15) -> 515121.09
A17: Content Assets | E17: =Schedules!E12 -> 16748096 | F17: =Schedules!F12 -> 16748096 | G17: =Schedules!G12 -> 16748096
A18: PP&E | E18: =Schedules!E4 -> 743983 | F18: =Schedules!F4 -> 743983 | G18: =Schedules!G4 -> 743983
A19: Capex | E19: =-SUM(E17:E18) -> -17492079 | F19: =-SUM(F17:F18) -> -17492079 | G19: =-SUM(G17:G18) -> -17492079
A20: Extraordinary Item
A21: UFCF | E21: =SUM(E10,E16,E19) -> 10627455 | F21: =SUM(F10,F16,F19) -> 13192222 | G21: =SUM(G10,G16,G19) -> 15588463
A22: Debt Repaid | E22: =Schedules!E22 -> -1006 | F22: =Schedules!F22 -> -1550 | G22: =Schedules!G22 -> -3632
A23: Interest Exp | E23: =Schedules!E25 -> -714624.02 | F23: =Schedules!F25 -> -714541.74 | G23: =Schedules!G25 -> -714348.95
A24: Difference Between Actual and Opt. Tax | E24: ='P&l Statement Forcasted '!E21-'Cash Flow Statement '!E5 -> 93189.176 | F24: ='P&l Statement Forcasted '!F21-'Cash Flow Statement '!F5 -> 93630.94 | G24: ='P&l Statement Forcasted '!G21-'Cash Flow Statement '!G5 -> 94844.262
A25: Net Cash Flow | E25: =SUM(E21:E24) -> 10005014 | F25: =SUM(F21:F24) -> 12569762 | G25: =SUM(G21:G24) -> 14965327
